main.py
blakport-1.0.0.dist-info/licenses/LICENSE
blakport-1.0.0.dist-info/METADATA
blakport-1.0.0.dist-info/WHEEL
blakport-1.0.0.dist-info/entry_points.txt
blakport-1.0.0.dist-info/top_level.txt
blakport-1.0.0.dist-info/RECORD
