Metadata-Version: 2.4
Name: blakport
Version: 1.0.0
Summary: Fast, lightweight FastAPI wrapper for exposing Ollama server to local network
Author: BlakPort Contributors
License-Expression: MIT
Project-URL: Homepage, https://github.com/yourusername/blakport
Project-URL: Documentation, https://github.com/yourusername/blakport#readme
Project-URL: Repository, https://github.com/yourusername/blakport
Project-URL: Issues, https://github.com/yourusername/blakport/issues
Keywords: ollama,fastapi,llm,local-network,api-gateway
Classifier: Development Status :: 4 - Beta
Classifier: Intended Audience :: Developers
Classifier: Programming Language :: Python :: 3
Classifier: Programming Language :: Python :: 3.8
Classifier: Programming Language :: Python :: 3.9
Classifier: Programming Language :: Python :: 3.10
Classifier: Programming Language :: Python :: 3.11
Classifier: Programming Language :: Python :: 3.12
Classifier: Topic :: Software Development :: Libraries :: Python Modules
Classifier: Topic :: Internet :: WWW/HTTP :: HTTP Servers
Requires-Python: >=3.8
License-File: LICENSE
Requires-Dist: fastapi>=0.104.0
Requires-Dist: uvicorn[standard]>=0.24.0
Requires-Dist: httpx>=0.25.0
Requires-Dist: pydantic>=2.0.0
Requires-Dist: requests>=2.31.0
Requires-Dist: click>=8.0.0
Requires-Dist: platformdirs>=3.0.0
Requires-Dist: tomli>=2.0.0; python_version < "3.11"
Provides-Extra: dev
Requires-Dist: pytest>=7.0; extra == "dev"
Requires-Dist: pytest-asyncio>=0.21.0; extra == "dev"
Requires-Dist: black>=23.0; extra == "dev"
Requires-Dist: ruff>=0.1.0; extra == "dev"
Dynamic: license-file
